cli/__init__.py
cli/param_cli.py
param_server/__init__.py
param_server/client.py
param_server/server.py
param_server/store.py
param_server-1.0.0.dist-info/METADATA
param_server-1.0.0.dist-info/WHEEL
param_server-1.0.0.dist-info/entry_points.txt
param_server-1.0.0.dist-info/RECORD
